yafw/__about__.py
yafw/__init__.py
yafw/cli.py
yafw/frealign_jobs.py
yafw/project_management.py
yafw-0.0.3.dist-info/METADATA
yafw-0.0.3.dist-info/WHEEL
yafw-0.0.3.dist-info/entry_points.txt
yafw-0.0.3.dist-info/licenses/LICENSE.txt
yafw-0.0.3.dist-info/RECORD
